ship_llm/__init__.py
ship_llm/ai.py
ship_llm/cache.py
ship_llm/clients.py
ship_llm/decorators.py
ship_llm/models.py
ship_llm/stream.py
ship_llm/utils.py
ship_llm-0.0.12.dist-info/LICENSE
ship_llm-0.0.12.dist-info/METADATA
ship_llm-0.0.12.dist-info/WHEEL
ship_llm-0.0.12.dist-info/RECORD
