Metadata-Version: 2.1
Name: ship-llm
Version: 0.0.12
Summary: Ship LLM: Ship Fast, Ship Now - Clean LLM Interface for Rapid Deployment
Author: Thoriq Akbar
Author-email: thoriqakbar00@gmail.com
Requires-Python: >=3.9,<4.0
Classifier: Programming Language :: Python :: 3
Classifier: Programming Language :: Python :: 3.9
Classifier: Programming Language :: Python :: 3.10
Classifier: Programming Language :: Python :: 3.11
Classifier: Programming Language :: Python :: 3.12
Requires-Dist: instructor
Requires-Dist: openai
Requires-Dist: pillow
Requires-Dist: pydantic
Requires-Dist: requests
